camel/__init__.py
camel/generators.py
camel/human.py
camel/logger.py
camel/py.typed
camel/agents/__init__.py
camel/agents/_types.py
camel/agents/_utils.py
camel/agents/base.py
camel/agents/chat_agent.py
camel/agents/critic_agent.py
camel/agents/deductive_reasoner_agent.py
camel/agents/embodied_agent.py
camel/agents/knowledge_graph_agent.py
camel/agents/mcp_agent.py
camel/agents/multi_hop_generator_agent.py
camel/agents/programmed_agent_instruction.py
camel/agents/repo_agent.py
camel/agents/role_assignment_agent.py
camel/agents/search_agent.py
camel/agents/task_agent.py
camel/agents/tool_agents/__init__.py
camel/agents/tool_agents/base.py
camel/agents/tool_agents/hugging_face_tool_agent.py
camel/benchmarks/__init__.py
camel/benchmarks/apibank.py
camel/benchmarks/apibench.py
camel/benchmarks/base.py
camel/benchmarks/browsecomp.py
camel/benchmarks/gaia.py
camel/benchmarks/nexus.py
camel/benchmarks/ragbench.py
camel/benchmarks/mock_website/README.md
camel/benchmarks/mock_website/mock_web.py
camel/benchmarks/mock_website/requirements.txt
camel/benchmarks/mock_website/task.json
camel/benchmarks/mock_website/shopping_mall/app.py
camel/bots/__init__.py
camel/bots/telegram_bot.py
camel/bots/discord/__init__.py
camel/bots/discord/discord_app.py
camel/bots/discord/discord_installation.py
camel/bots/discord/discord_store.py
camel/bots/slack/__init__.py
camel/bots/slack/models.py
camel/bots/slack/slack_app.py
camel/configs/__init__.py
camel/configs/aihubmix_config.py
camel/configs/aiml_config.py
camel/configs/amd_config.py
camel/configs/anthropic_config.py
camel/configs/base_config.py
camel/configs/bedrock_config.py
camel/configs/cerebras_config.py
camel/configs/cohere_config.py
camel/configs/cometapi_config.py
camel/configs/crynux_config.py
camel/configs/deepseek_config.py
camel/configs/gemini_config.py
camel/configs/groq_config.py
camel/configs/internlm_config.py
camel/configs/litellm_config.py
camel/configs/lmstudio_config.py
camel/configs/minimax_config.py
camel_ai-0.2.82.dist-info/METADATA
camel_ai-0.2.82.dist-info/WHEEL
camel_ai-0.2.82.dist-info/licenses/LICENSE
camel_ai-0.2.82.dist-info/RECORD
