Metadata-Version: 2.4
Name: camel-ai
Version: 0.2.82
Summary: Communicative Agents for AI Society Study
Project-URL: Homepage, https://www.camel-ai.org/
Project-URL: Repository, https://github.com/camel-ai/camel
Project-URL: Documentation, https://docs.camel-ai.org
Author: CAMEL-AI.org
License-Expression: Apache-2.0
License-File: LICENSE
Keywords: ai-societies,artificial-intelligence,communicative-ai,cooperative-ai,deep-learning,large-language-models,multi-agent-systems,natural-language-processing
Requires-Python: <3.15,>=3.10
Requires-Dist: astor>=0.8.1
Requires-Dist: colorama<0.5,>=0.4.6
Requires-Dist: docstring-parser<0.18,>=0.17.0
Requires-Dist: google-search-results>=2.4.2
Requires-Dist: httpx<1.0.0dev,>=0.28.0
Requires-Dist: jsonschema<5,>=4
Requires-Dist: mcp>=1.3.0
Requires-Dist: openai>=1.86.0
Requires-Dist: pillow>=10.0.0
Requires-Dist: psutil<6,>=5.9.8
Requires-Dist: pydantic<=2.12.0,>=2.10.6
Requires-Dist: tiktoken<0.8,>=0.7.0
Requires-Dist: websockets<15.1,>=13.0
Provides-Extra: all
Requires-Dist: aci-sdk>=1.0.0b1; extra == 'all'
Requires-Dist: agentops<0.4,>=0.3.21; extra == 'all'
Requires-Dist: aiosqlite<0.21,>=0.20.0; extra == 'all'
Requires-Dist: anthropic<0.50.0,>=0.47.0; extra == 'all'
Requires-Dist: apify-client<2,>=1.8.1; extra == 'all'
Requires-Dist: arxiv2text<0.2,>=0.1.14; extra == 'all'
Requires-Dist: arxiv<3,>=2.1.3; extra == 'all'
Requires-Dist: azure-storage-blob<13,>=12.21.0; extra == 'all'
Requires-Dist: beautifulsoup4<5,>=4; extra == 'all'
Requires-Dist: botocore<2,>=1.35.3; extra == 'all'
Requires-Dist: chromadb<1.0.0,>=0.6.0; extra == 'all'
Requires-Dist: chunkr-ai<0.1.0,>=0.0.50; extra == 'all'
Requires-Dist: cohere<6,>=5.11.0; extra == 'all'
Requires-Dist: crawl4ai>=0.4.0; extra == 'all'
Requires-Dist: dappier<0.4,>=0.3.3; extra == 'all'
Requires-Dist: datacommons-pandas<0.0.4,>=0.0.3; extra == 'all'
Requires-Dist: datacommons<2,>=1.4.3; extra == 'all'
Requires-Dist: datasets<4,>=3; extra == 'all'
Requires-Dist: daytona-sdk>=0.20.0; extra == 'all'
Requires-Dist: ddgs<10,>=9.0.0; extra == 'all'
Requires-Dist: diffusers<0.26,>=0.25.0; extra == 'all'
Requires-Dist: discord-py<3,>=2.3.2; extra == 'all'
Requires-Dist: docker<8,>=7.1.0; extra == 'all'
Requires-Dist: docx2txt<0.9,>=0.8; extra == 'all'
Requires-Dist: docx>=0.2.4; extra == 'all'
Requires-Dist: duckdb>=1.4.3; extra == 'all'
Requires-Dist: e2b-code-interpreter<2,>=1.0.3; extra == 'all'
Requires-Dist: exa-py<2,>=1.10.0; extra == 'all'
Requires-Dist: faiss-cpu<2,>=1.7.2; extra == 'all'
Requires-Dist: fastapi>=0.115.11; extra == 'all'
Requires-Dist: ffmpeg-python<0.3,>=0.2.0; extra == 'all'
Requires-Dist: firecrawl-py<2,>=1.0.0; extra == 'all'
Requires-Dist: fish-audio-sdk>=1.0.0; extra == 'all'
Requires-Dist: flask>=2.0; extra == 'all'
Requires-Dist: google-api-python-client==2.166.0; extra == 'all'
Requires-Dist: google-auth-httplib2==0.2.0; extra == 'all'
Requires-Dist: google-auth-oauthlib==1.2.1; extra == 'all'
Requires-Dist: google-auth<3.0.0,>=2.0.0; extra == 'all'
Requires-Dist: google-cloud-aiplatform>=1.111.0; extra == 'all'
Requires-Dist: google-cloud-storage<3,>=2.18.0; extra == 'all'
Requires-Dist: google-genai>=1.13.0; extra == 'all'
Requires-Dist: googlemaps<5,>=4.10.0; extra == 'all'
Requires-Dist: gradio<4,>=3; extra == 'all'
Requires-Dist: grpcio>=1.72.0; extra == 'all'
Requires-Dist: html2text>=2024.2.26; extra == 'all'
Requires-Dist: httplib2>=0.31.0; extra == 'all'
Requires-Dist: ibm-watsonx-ai>=1.3.11; extra == 'all'
Requires-Dist: imageio[pyav]<3,>=2.34.2; extra == 'all'
Requires-Dist: ipykernel<7,>=6.0.0; extra == 'all'
Requires-Dist: jupyter-client<9,>=8.6.2; extra == 'all'
Requires-Dist: langfuse>=2.60.5; extra == 'all'
Requires-Dist: linkup-sdk<0.3,>=0.2.1; extra == 'all'
Requires-Dist: litellm<2,>=1.38.1; extra == 'all'
Requires-Dist: markitdown>=0.1.1; (python_version >= '3.13') and extra == 'all'
Requires-Dist: math-verify<0.8,>=0.7.0; extra == 'all'
Requires-Dist: mcp>=1.3.0; extra == 'all'
Requires-Dist: mem0ai>=0.1.67; extra == 'all'
Requires-Dist: microsandbox>=0.1.8; extra == 'all'
Requires-Dist: mistralai<2,>=1.1.0; extra == 'all'
Requires-Dist: mock<6,>=5; extra == 'all'
Requires-Dist: mypy<2,>=1.5.1; extra == 'all'
Requires-Dist: nebula3-python==3.8.2; extra == 'all'
Requires-Dist: neo4j<6,>=5.18.0; extra == 'all'
Requires-Dist: networkx<4,>=3.4.2; extra == 'all'
Requires-Dist: notion-client<3,>=2.2.1; extra == 'all'
Requires-Dist: numpy<=2.2,>=1.2; extra == 'all'
Requires-Dist: onnxruntime<=1.19.2; extra == 'all'
Requires-Dist: openapi-spec-validator<0.8,>=0.7.1; extra == 'all'
Requires-Dist: opencv-python>=4.11.0.86; extra == 'all'
Requires-Dist: openpyxl>=3.1.5; extra == 'all'
Requires-Dist: pandas>=2; extra == 'all'
Requires-Dist: pgvector<0.3,>=0.2.4; extra == 'all'
Requires-Dist: playwright>=1.50.0; extra == 'all'
Requires-Dist: prance<24,>=23.6.21.0; extra == 'all'
Requires-Dist: praw<8,>=7.7.1; extra == 'all'
Requires-Dist: pre-commit<4,>=3; extra == 'all'
Requires-Dist: protobuf>=6.0.0; extra == 'all'
Requires-Dist: psycopg[binary]<4,>=3.1.18; extra == 'all'
Requires-Dist: pyautogui<0.10,>=0.9.54; extra == 'all'
Requires-Dist: pydub<0.26,>=0.25.1; extra == 'all'
Requires-Dist: pygithub<3,>=2.6.0; extra == 'all'
Requires-Dist: pylatex>=1.4.2; extra == 'all'
Requires-Dist: pymilvus<3,>=2.4.0; extra == 'all'
Requires-Dist: pymupdf<2,>=1.22.5; extra == 'all'
Requires-Dist: pyobvector>=0.1.18; (python_version < '3.13') and extra == 'all'
Requires-Dist: pyowm<4,>=3.3.0; extra == 'all'
Requires-Dist: pytelegrambotapi<5,>=4.18.0; extra == 'all'
Requires-Dist: pytesseract>=0.3.13; extra == 'all'
Requires-Dist: pytest-asyncio<0.24,>=0.23.0; extra == 'all'
Requires-Dist: pytest-cov<5,>=4; extra == 'all'
Requires-Dist: pytest<8,>=7; extra == 'all'
Requires-Dist: python-pptx>=1.0.2; extra == 'all'
Requires-Dist: pytidb>=0.0.13; extra == 'all'
Requires-Dist: qdrant-client<2,>=1.9.0; extra == 'all'
Requires-Dist: rank-bm25<0.3,>=0.2.2; extra == 'all'
Requires-Dist: rasterio>=1.4.4; extra == 'all'
Requires-Dist: redis<6,>=5.0.6; extra == 'all'
Requires-Dist: reka-api<4,>=3.0.8; extra == 'all'
Requires-Dist: reportlab>=4.4.2; extra == 'all'
Requires-Dist: requests-oauthlib<2,>=1.3.1; extra == 'all'
Requires-Dist: resend<3,>=2.0.0; extra == 'all'
Requires-Dist: rlcard<1.3.0,>=1.0.0; extra == 'all'
Requires-Dist: rouge<2,>=1.0.1; extra == 'all'
Requires-Dist: ruptures>=1.1.10; extra == 'all'
Requires-Dist: scenedetect>=0.6.5.2; extra == 'all'
Requires-Dist: scholarly[tor]==1.7.11; extra == 'all'
Requires-Dist: scikit-image>=0.25.2; extra == 'all'
Requires-Dist: scipy>=1.15.3; extra == 'all'
Requires-Dist: scrapegraph-py<2,>=1.12.0; extra == 'all'
Requires-Dist: sentencepiece<0.3,>=0.2; extra == 'all'
Requires-Dist: slack-bolt<2,>=1.20.1; extra == 'all'
Requires-Dist: slack-sdk<4,>=3.27.2; extra == 'all'
Requires-Dist: soundfile<0.14,>=0.13; extra == 'all'
Requires-Dist: statsmodels>=0.14.6; extra == 'all'
Requires-Dist: stripe<12,>=11.3.0; extra == 'all'
Requires-Dist: surrealdb>=1.0.6; extra == 'all'
Requires-Dist: sympy<2,>=1.13.3; extra == 'all'
Requires-Dist: tabulate>=0.9.0; extra == 'all'
Requires-Dist: tavily-python<0.6,>=0.5.0; extra == 'all'
Requires-Dist: textblob<0.18,>=0.17.1; extra == 'all'
Requires-Dist: transformers<5,>=4; extra == 'all'
Requires-Dist: tree-sitter-python<0.24,>=0.23.6; extra == 'all'
Requires-Dist: tree-sitter<0.24,>=0.23.2; extra == 'all'
Requires-Dist: typer>=0.15.2; extra == 'all'
Requires-Dist: types-colorama<0.5,>=0.4.15; extra == 'all'
Requires-Dist: types-mock<6,>=5.1.0; extra == 'all'
Requires-Dist: types-pyyaml<7,>=6.0.12; extra == 'all'
Requires-Dist: types-requests<3,>=2.31.0; extra == 'all'
Requires-Dist: types-setuptools<70,>=69.2.0; extra == 'all'
Requires-Dist: types-tqdm<5,>=4.66.0; extra == 'all'
Requires-Dist: unstructured==0.16.20; (python_version < '3.13') and extra == 'all'
Requires-Dist: weaviate-client>=4.15.0; extra == 'all'
Requires-Dist: websockets<15.1,>=13.0; extra == 'all'
Requires-Dist: wikipedia<2,>=1; extra == 'all'
Requires-Dist: wolframalpha<6,>=5.0.0; extra == 'all'
Requires-Dist: xls2xlsx>=0.2.0; extra == 'all'
Requires-Dist: yt-dlp<2025,>=2024.11.4; extra == 'all'
Provides-Extra: communication-tools
Requires-Dist: discord-py<3,>=2.3.2; extra == 'communication-tools'
Requires-Dist: notion-client<3,>=2.2.1; extra == 'communication-tools'
Requires-Dist: praw<8,>=7.7.1; extra == 'communication-tools'
Requires-Dist: pygithub<3,>=2.6.0; extra == 'communication-tools'
Requires-Dist: pytelegrambotapi<5,>=4.18.0; extra == 'communication-tools'
Requires-Dist: resend<3,>=2.0.0; extra == 'communication-tools'
Requires-Dist: slack-bolt<2,>=1.20.1; extra == 'communication-tools'
Requires-Dist: slack-sdk<4,>=3.27.2; extra == 'communication-tools'
Provides-Extra: data-tools
Requires-Dist: aiosqlite<0.21,>=0.20.0; extra == 'data-tools'
Requires-Dist: datacommons-pandas<0.0.4,>=0.0.3; extra == 'data-tools'
Requires-Dist: datacommons<2,>=1.4.3; extra == 'data-tools'
Requires-Dist: math-verify<0.8,>=0.7.0; extra == 'data-tools'
Requires-Dist: networkx<4,>=3.4.2; extra == 'data-tools'
Requires-Dist: numpy<=2.2,>=1.2; extra == 'data-tools'
Requires-Dist: pandas>=2; extra == 'data-tools'
Requires-Dist: rouge<2,>=1.0.1; extra == 'data-tools'
Requires-Dist: stripe<12,>=11.3.0; extra == 'data-tools'
Requires-Dist: textblob<0.18,>=0.17.1; extra == 'data-tools'
Provides-Extra: dev
Requires-Dist: flask>=2.0; extra == 'dev'
Requires-Dist: gradio<4,>=3; extra == 'dev'
Requires-Dist: mock<6,>=5; extra == 'dev'
Requires-Dist: mypy<2,>=1.5.1; extra == 'dev'
Requires-Dist: pre-commit<4,>=3; extra == 'dev'
Requires-Dist: pytest-asyncio<0.24,>=0.23.0; extra == 'dev'
Requires-Dist: pytest-cov<5,>=4; extra == 'dev'
Requires-Dist: pytest<8,>=7; extra == 'dev'
Requires-Dist: ruff<0.8,>=0.7; extra == 'dev'
Requires-Dist: toml>=0.10.2; extra == 'dev'
Requires-Dist: types-colorama<0.5,>=0.4.15; extra == 'dev'
Requires-Dist: types-mock<6,>=5.1.0; extra == 'dev'
Requires-Dist: types-pyyaml<7,>=6.0.12; extra == 'dev'
Requires-Dist: types-requests<3,>=2.31.0; extra == 'dev'
Requires-Dist: types-setuptools<70,>=69.2.0; extra == 'dev'
Requires-Dist: types-tqdm<5,>=4.66.0; extra == 'dev'
Requires-Dist: uv<0.8,>=0.7.0; extra == 'dev'
Provides-Extra: dev-tools
Requires-Dist: aci-sdk>=1.0.0b1; extra == 'dev-tools'
Requires-Dist: agentops<0.4,>=0.3.21; extra == 'dev-tools'
Requires-Dist: daytona-sdk>=0.20.0; extra == 'dev-tools'
Requires-Dist: docker<8,>=7.1.0; extra == 'dev-tools'
Requires-Dist: e2b-code-interpreter<2,>=1.0.3; extra == 'dev-tools'
Requires-Dist: ipykernel<7,>=6.0.0; extra == 'dev-tools'
Requires-Dist: jupyter-client<9,>=8.6.2; extra == 'dev-tools'
Requires-Dist: langfuse>=2.60.5; extra == 'dev-tools'
Requires-Dist: mcp>=1.3.0; extra == 'dev-tools'
Requires-Dist: microsandbox>=0.1.8; extra == 'dev-tools'
Requires-Dist: tree-sitter-python<0.24,>=0.23.6; extra == 'dev-tools'
Requires-Dist: tree-sitter<0.24,>=0.23.2; extra == 'dev-tools'
Requires-Dist: typer>=0.15.2; extra == 'dev-tools'
Provides-Extra: docs
Requires-Dist: docutils<0.20.0; extra == 'docs'
Requires-Dist: myst-parser; extra == 'docs'
Requires-Dist: nbsphinx; extra == 'docs'
Requires-Dist: sphinx-book-theme; extra == 'docs'
Requires-Dist: sphinx<8,>=7; extra == 'docs'
Requires-Dist: sphinxext-rediraffe<0.3,>=0.2.7; extra == 'docs'
Provides-Extra: document-tools
Requires-Dist: beautifulsoup4<5,>=4; extra == 'document-tools'
Requires-Dist: chunkr-ai<0.1.0,>=0.0.50; extra == 'document-tools'
Requires-Dist: crawl4ai>=0.3.745; extra == 'document-tools'
Requires-Dist: docx2txt<0.9,>=0.8; extra == 'document-tools'
Requires-Dist: docx>=0.2.4; extra == 'document-tools'
Requires-Dist: markitdown>=0.1.1; (python_version >= '3.13') and extra == 'document-tools'
Requires-Dist: numpy<=2.2,>=1.2; extra == 'document-tools'
Requires-Dist: onnxruntime<=1.19.2; extra == 'document-tools'
Requires-Dist: openapi-spec-validator<0.8,>=0.7.1; extra == 'document-tools'
Requires-Dist: openpyxl>=3.1.5; extra == 'document-tools'
Requires-Dist: prance<24,>=23.6.21.0; extra == 'document-tools'
Requires-Dist: pylatex>=1.4.2; extra == 'document-tools'
Requires-Dist: pymupdf<2,>=1.22.5; extra == 'document-tools'
Requires-Dist: python-pptx>=1.0.2; extra == 'document-tools'
Requires-Dist: reportlab>=4.4.2; extra == 'document-tools'
Requires-Dist: tabulate>=0.9.0; extra == 'document-tools'
Requires-Dist: unstructured==0.16.20; (python_version < '3.13') and extra == 'document-tools'
Requires-Dist: xls2xlsx>=0.2.0; extra == 'document-tools'
Provides-Extra: earth-science
Requires-Dist: matplotlib>=3.10.7; extra == 'earth-science'
Requires-Dist: numpy<=2.2,>=1.2; extra == 'earth-science'
Requires-Dist: opencv-python>=4.11.0.86; extra == 'earth-science'
Requires-Dist: pandas>=2; extra == 'earth-science'
Requires-Dist: rasterio>=1.4.4; extra == 'earth-science'
Requires-Dist: ruptures>=1.1.10; extra == 'earth-science'
Requires-Dist: scikit-image>=0.25.2; extra == 'earth-science'
Requires-Dist: scipy>=1.15.3; extra == 'earth-science'
Requires-Dist: statsmodels>=0.14.6; extra == 'earth-science'
Provides-Extra: eigent
Requires-Dist: anthropic<0.50.0,>=0.47.0; extra == 'eigent'
Requires-Dist: datasets<4,>=3; extra == 'eigent'
Requires-Dist: docx>=0.2.4; extra == 'eigent'
Requires-Dist: exa-py<2,>=1.10.0; extra == 'eigent'
Requires-Dist: ffmpeg-python<0.3,>=0.2.0; extra == 'eigent'
Requires-Dist: google-api-python-client==2.166.0; extra == 'eigent'
Requires-Dist: google-auth-httplib2==0.2.0; extra == 'eigent'
Requires-Dist: google-auth-oauthlib==1.2.1; extra == 'eigent'
Requires-Dist: httplib2>=0.31.0; extra == 'eigent'
Requires-Dist: imageio[pyav]<3,>=2.34.2; extra == 'eigent'
Requires-Dist: markitdown>=0.1.1; (python_version >= '3.13') and extra == 'eigent'
Requires-Dist: markitdown[all]>=0.1.1; (python_version < '3.13') and extra == 'eigent'
Requires-Dist: mcp-server-fetch==2025.1.17; extra == 'eigent'
Requires-Dist: mcp-simple-arxiv==0.2.2; extra == 'eigent'
Requires-Dist: numpy<=2.2,>=1.2; extra == 'eigent'
Requires-Dist: onnxruntime<=1.19.2; extra == 'eigent'
Requires-Dist: openpyxl>=3.1.5; extra == 'eigent'
Requires-Dist: pandas>=2; extra == 'eigent'
Requires-Dist: pydub<0.26,>=0.25.1; extra == 'eigent'
Requires-Dist: pylatex>=1.4.2; extra == 'eigent'
Requires-Dist: pytesseract>=0.3.13; extra == 'eigent'
Requires-Dist: python-dotenv<2,>=1.0.0; extra == 'eigent'
Requires-Dist: python-pptx>=1.0.2; extra == 'eigent'
Requires-Dist: reportlab>=4.4.2; extra == 'eigent'
Requires-Dist: requests-oauthlib<2,>=1.3.1; extra == 'eigent'
Requires-Dist: scenedetect>=0.6.5.2; extra == 'eigent'
Requires-Dist: slack-sdk<4,>=3.27.2; extra == 'eigent'
Requires-Dist: tabulate>=0.9.0; extra == 'eigent'
Requires-Dist: websockets<15.1,>=13.0; extra == 'eigent'
Requires-Dist: wikipedia<2,>=1; extra == 'eigent'
Requires-Dist: xls2xlsx>=0.2.0; extra == 'eigent'
Requires-Dist: yt-dlp<2025,>=2024.11.4; extra == 'eigent'
Provides-Extra: huggingface
Requires-Dist: datasets<4,>=3; extra == 'huggingface'
Requires-Dist: diffusers<0.26,>=0.25.0; extra == 'huggingface'
Requires-Dist: huggingface-hub; extra == 'huggingface'
Requires-Dist: sentencepiece<0.3,>=0.2; extra == 'huggingface'
Requires-Dist: soundfile<0.14,>=0.13; extra == 'huggingface'
Requires-Dist: transformers<5,>=4; extra == 'huggingface'
Provides-Extra: media-tools
Requires-Dist: ffmpeg-python<0.3,>=0.2.0; extra == 'media-tools'
Requires-Dist: imageio[pyav]<3,>=2.34.2; extra == 'media-tools'
Requires-Dist: pydub<0.26,>=0.25.1; extra == 'media-tools'
Requires-Dist: pytesseract>=0.3.13; extra == 'media-tools'
Requires-Dist: scenedetect>=0.6.5.2; extra == 'media-tools'
Requires-Dist: yt-dlp<2025,>=2024.11.4; extra == 'media-tools'
Provides-Extra: model-platforms
Requires-Dist: anthropic<0.50.0,>=0.47.0; extra == 'model-platforms'
Requires-Dist: cohere<6,>=5.11.0; extra == 'model-platforms'
Requires-Dist: fish-audio-sdk>=1.0.0; extra == 'model-platforms'
Requires-Dist: ibm-watsonx-ai>=1.3.11; extra == 'model-platforms'
Requires-Dist: litellm<2,>=1.38.1; extra == 'model-platforms'
Requires-Dist: mistralai<2,>=1.1.0; extra == 'model-platforms'
Requires-Dist: reka-api<4,>=3.0.8; extra == 'model-platforms'
Provides-Extra: owl
Requires-Dist: aci-sdk>=1.0.0b1; extra == 'owl'
Requires-Dist: anthropic<0.50.0,>=0.47.0; extra == 'owl'
Requires-Dist: beautifulsoup4<5,>=4; extra == 'owl'
Requires-Dist: chunkr-ai<0.1.0,>=0.0.50; extra == 'owl'
Requires-Dist: chunkr-ai>=0.0.41; extra == 'owl'
Requires-Dist: crawl4ai>=0.3.745; extra == 'owl'
Requires-Dist: datasets<4,>=3; extra == 'owl'
Requires-Dist: ddgs<10,>=9.0.0; extra == 'owl'
Requires-Dist: docx2txt<0.9,>=0.8; extra == 'owl'
Requires-Dist: docx>=0.2.4; extra == 'owl'
Requires-Dist: e2b-code-interpreter<2,>=1.0.3; extra == 'owl'
Requires-Dist: exa-py<2,>=1.10.0; extra == 'owl'
Requires-Dist: ffmpeg-python<0.3,>=0.2.0; extra == 'owl'
Requires-Dist: html2text>=2024.2.26; extra == 'owl'
Requires-Dist: imageio[pyav]<3,>=2.34.2; extra == 'owl'
Requires-Dist: markitdown>=0.1.1; (python_version >= '3.13') and extra == 'owl'
Requires-Dist: mcp-server-fetch==2025.1.17; extra == 'owl'
Requires-Dist: mcp-simple-arxiv==0.2.2; extra == 'owl'
Requires-Dist: numpy<=2.2,>=1.2; extra == 'owl'
Requires-Dist: onnxruntime<=1.19.2; extra == 'owl'
Requires-Dist: openapi-spec-validator<0.8,>=0.7.1; extra == 'owl'
Requires-Dist: openpyxl>=3.1.5; extra == 'owl'
Requires-Dist: pandas>=2; extra == 'owl'
Requires-Dist: playwright>=1.50.0; extra == 'owl'
Requires-Dist: prance<24,>=23.6.21.0; extra == 'owl'
Requires-Dist: pyautogui<0.10,>=0.9.54; extra == 'owl'
Requires-Dist: pydub<0.26,>=0.25.1; extra == 'owl'
Requires-Dist: pylatex>=1.4.2; extra == 'owl'
Requires-Dist: pymupdf<2,>=1.22.5; extra == 'owl'
Requires-Dist: pytesseract>=0.3.13; extra == 'owl'
Requires-Dist: python-dotenv<2,>=1.0.0; extra == 'owl'
Requires-Dist: python-pptx>=1.0.2; extra == 'owl'
Requires-Dist: reportlab>=4.4.2; extra == 'owl'
Requires-Dist: requests-oauthlib<2,>=1.3.1; extra == 'owl'
Requires-Dist: rouge<2,>=1.0.1; extra == 'owl'
Requires-Dist: scenedetect>=0.6.5.2; extra == 'owl'
Requires-Dist: scrapegraph-py<2,>=1.12.0; extra == 'owl'
Requires-Dist: sentencepiece<0.3,>=0.2; extra == 'owl'
Requires-Dist: soundfile<0.14,>=0.13; extra == 'owl'
Requires-Dist: tabulate>=0.9.0; extra == 'owl'
Requires-Dist: transformers<5,>=4; extra == 'owl'
Requires-Dist: tree-sitter-python<0.24,>=0.23.6; extra == 'owl'
Requires-Dist: tree-sitter<0.24,>=0.23.2; extra == 'owl'
Requires-Dist: typer>=0.15.2; extra == 'owl'
Requires-Dist: unstructured==0.16.20; (python_version < '3.13') and extra == 'owl'
Requires-Dist: websockets<15.1,>=13.0; extra == 'owl'
Requires-Dist: wikipedia<2,>=1; extra == 'owl'
Requires-Dist: xls2xlsx>=0.2.0; extra == 'owl'
Requires-Dist: yt-dlp<2025,>=2024.11.4; extra == 'owl'
Provides-Extra: rag
Requires-Dist: chromadb<1.0.0,>=0.6.0; extra == 'rag'
Requires-Dist: chunkr-ai<0.1.0,>=0.0.50; extra == 'rag'
Requires-Dist: cohere<6,>=5.11.0; extra == 'rag'
Requires-Dist: crawl4ai>=0.3.745; extra == 'rag'
Requires-Dist: faiss-cpu<2,>=1.7.2; extra == 'rag'
Requires-Dist: google-genai>=1.13.0; extra == 'rag'
Requires-Dist: grpcio>=1.72.0; extra == 'rag'
Requires-Dist: nebula3-python==3.8.2; extra == 'rag'
Requires-Dist: neo4j<6,>=5.18.0; extra == 'rag'
Requires-Dist: numpy<=2.2,>=1.2; extra == 'rag'
Requires-Dist: protobuf>=6.0.0; extra == 'rag'
Requires-Dist: pymilvus<3,>=2.4.0; extra == 'rag'
Requires-Dist: pyobvector>=0.1.18; (python_version < '3.13') and extra == 'rag'
Requires-Dist: pytidb>=0.0.13; extra == 'rag'
Requires-Dist: qdrant-client<2,>=1.9.0; extra == 'rag'
Requires-Dist: rank-bm25<0.3,>=0.2.2; extra == 'rag'
Requires-Dist: unstructured==0.16.20; (python_version < '3.13') and extra == 'rag'
Requires-Dist: weaviate-client>=4.15.0; extra == 'rag'
Provides-Extra: research-tools
Requires-Dist: arxiv2text<0.2,>=0.1.14; extra == 'research-tools'
Requires-Dist: arxiv<3,>=2.1.3; extra == 'research-tools'
Requires-Dist: scholarly[tor]==1.7.11; extra == 'research-tools'
Provides-Extra: storage
Requires-Dist: azure-storage-blob<13,>=12.21.0; extra == 'storage'
Requires-Dist: botocore<2,>=1.35.3; extra == 'storage'
Requires-Dist: chromadb<1.0.0,>=0.6.0; extra == 'storage'
Requires-Dist: duckdb>=1.4.3; extra == 'storage'
Requires-Dist: faiss-cpu<2,>=1.7.2; extra == 'storage'
Requires-Dist: google-cloud-storage<3,>=2.18.0; extra == 'storage'
Requires-Dist: grpcio>=1.72.0; extra == 'storage'
Requires-Dist: mem0ai>=0.1.73; extra == 'storage'
Requires-Dist: nebula3-python==3.8.2; extra == 'storage'
Requires-Dist: neo4j<6,>=5.18.0; extra == 'storage'
Requires-Dist: pgvector<0.3,>=0.2.4; extra == 'storage'
Requires-Dist: protobuf>=6.0.0; extra == 'storage'
Requires-Dist: psycopg[binary]<4,>=3.1.18; extra == 'storage'
Requires-Dist: pymilvus<3,>=2.4.0; extra == 'storage'
Requires-Dist: pyobvector>=0.1.18; (python_version < '3.13') and extra == 'storage'
Requires-Dist: pytidb>=0.0.13; extra == 'storage'
Requires-Dist: qdrant-client<2,>=1.9.0; extra == 'storage'
Requires-Dist: redis<6,>=5.0.6; extra == 'storage'
Requires-Dist: surrealdb>=1.0.6; extra == 'storage'
Requires-Dist: weaviate-client>=4.15.0; extra == 'storage'
Provides-Extra: web-tools
Requires-Dist: apify-client<2,>=1.8.1; extra == 'web-tools'
Requires-Dist: beautifulsoup4<5,>=4; extra == 'web-tools'
Requires-Dist: dappier<0.4,>=0.3.3; extra == 'web-tools'
Requires-Dist: ddgs<10,>=9.0.0; extra == 'web-tools'
Requires-Dist: exa-py<2,>=1.10.0; extra == 'web-tools'
Requires-Dist: fastapi>=0.115.11; extra == 'web-tools'
Requires-Dist: firecrawl-py<2,>=1.0.0; extra == 'web-tools'
Requires-Dist: google-api-python-client==2.166.0; extra == 'web-tools'
Requires-Dist: google-auth-httplib2==0.2.0; extra == 'web-tools'
Requires-Dist: google-auth-oauthlib==1.2.1; extra == 'web-tools'
Requires-Dist: google-auth<3.0.0,>=2.0.0; extra == 'web-tools'
Requires-Dist: googlemaps<5,>=4.10.0; extra == 'web-tools'
Requires-Dist: html2text>=2024.2.26; extra == 'web-tools'
Requires-Dist: linkup-sdk<0.3,>=0.2.1; extra == 'web-tools'
Requires-Dist: playwright>=1.50.0; extra == 'web-tools'
Requires-Dist: pyowm<4,>=3.3.0; extra == 'web-tools'
Requires-Dist: requests-oauthlib<2,>=1.3.1; extra == 'web-tools'
Requires-Dist: scrapegraph-py<2,>=1.12.0; extra == 'web-tools'
Requires-Dist: sympy<2,>=1.13.3; extra == 'web-tools'
Requires-Dist: tavily-python<0.6,>=0.5.0; extra == 'web-tools'
Requires-Dist: websockets<15.1,>=13.0; extra == 'web-tools'
Requires-Dist: wikipedia<2,>=1; extra == 'web-tools'
Requires-Dist: wolframalpha<6,>=5.0.0; extra == 'web-tools'
